{
  "openapi": "3.0.0",
  "paths": {
    "/api/v1/types/slug/{slug}": {
      "get": {
        "operationId": "getTypeBySlug",
        "parameters": [
          {
            "name": "slug",
            "required": true,
            "in": "path",
            "schema": { "type": "string" }
          }
        ],
        "responses": {
          "200": {
            "description": "",
            "content": {
              "application/json": {
                "schema": { "$ref": "#/components/schemas/TypeModel" }
              }
            }
          },
          "400": {
            "description": "",
            "content": {
              "application/json": {
                "schema": { "$ref": "#/components/schemas/ApiErrorDto" }
              }
            }
          },
          "401": {
            "description": "",
            "content": {
              "application/json": {
                "schema": { "$ref": "#/components/schemas/ApiErrorDto" }
              }
            }
          },
          "403": {
            "description": "",
            "content": {
              "application/json": {
                "schema": { "$ref": "#/components/schemas/ApiErrorDto" }
              }
            }
          },
          "404": {
            "description": "",
            "content": {
              "application/json": {
                "schema": { "$ref": "#/components/schemas/ApiErrorDto" }
              }
            }
          },
          "500": {
            "description": "",
            "content": {
              "application/json": {
                "schema": { "$ref": "#/components/schemas/ApiErrorDto" }
              }
            }
          }
        },
        "summary": "",
        "tags": ["Legal gazette - public API"]
      }
    },
    "/api/v1/types/common": {
      "get": {
        "operationId": "getCommonAdvertTypes",
        "parameters": [],
        "responses": {
          "200": {
            "description": "",
            "content": {
              "application/json": {
                "schema": { "$ref": "#/components/schemas/GetTypesDto" }
              }
            }
          },
          "400": {
            "description": "",
            "content": {
              "application/json": {
                "schema": { "$ref": "#/components/schemas/ApiErrorDto" }
              }
            }
          },
          "401": {
            "description": "",
            "content": {
              "application/json": {
                "schema": { "$ref": "#/components/schemas/ApiErrorDto" }
              }
            }
          },
          "403": {
            "description": "",
            "content": {
              "application/json": {
                "schema": { "$ref": "#/components/schemas/ApiErrorDto" }
              }
            }
          },
          "404": {
            "description": "",
            "content": {
              "application/json": {
                "schema": { "$ref": "#/components/schemas/ApiErrorDto" }
              }
            }
          },
          "500": {
            "description": "",
            "content": {
              "application/json": {
                "schema": { "$ref": "#/components/schemas/ApiErrorDto" }
              }
            }
          }
        },
        "summary": "",
        "tags": ["Legal gazette - public API"]
      }
    },
    "/api/v1/types/{id}": {
      "get": {
        "operationId": "getType",
        "parameters": [
          {
            "name": "id",
            "required": true,
            "in": "path",
            "schema": { "type": "string" }
          }
        ],
        "responses": {
          "200": {
            "description": "",
            "content": {
              "application/json": {
                "schema": { "$ref": "#/components/schemas/TypeModel" }
              }
            }
          },
          "400": {
            "description": "",
            "content": {
              "application/json": {
                "schema": { "$ref": "#/components/schemas/ApiErrorDto" }
              }
            }
          },
          "401": {
            "description": "",
            "content": {
              "application/json": {
                "schema": { "$ref": "#/components/schemas/ApiErrorDto" }
              }
            }
          },
          "403": {
            "description": "",
            "content": {
              "application/json": {
                "schema": { "$ref": "#/components/schemas/ApiErrorDto" }
              }
            }
          },
          "404": {
            "description": "",
            "content": {
              "application/json": {
                "schema": { "$ref": "#/components/schemas/ApiErrorDto" }
              }
            }
          },
          "500": {
            "description": "",
            "content": {
              "application/json": {
                "schema": { "$ref": "#/components/schemas/ApiErrorDto" }
              }
            }
          }
        },
        "summary": "",
        "tags": ["Legal gazette - public API"]
      }
    },
    "/api/v1/types": {
      "get": {
        "operationId": "getTypes",
        "parameters": [
          {
            "name": "excludeUnassignable",
            "required": false,
            "in": "query",
            "description": "Filter out unassignable advert types",
            "schema": { "type": "boolean" }
          }
        ],
        "responses": {
          "200": {
            "description": "",
            "content": {
              "application/json": {
                "schema": { "$ref": "#/components/schemas/GetTypesDto" }
              }
            }
          },
          "400": {
            "description": "",
            "content": {
              "application/json": {
                "schema": { "$ref": "#/components/schemas/ApiErrorDto" }
              }
            }
          },
          "401": {
            "description": "",
            "content": {
              "application/json": {
                "schema": { "$ref": "#/components/schemas/ApiErrorDto" }
              }
            }
          },
          "403": {
            "description": "",
            "content": {
              "application/json": {
                "schema": { "$ref": "#/components/schemas/ApiErrorDto" }
              }
            }
          },
          "404": {
            "description": "",
            "content": {
              "application/json": {
                "schema": { "$ref": "#/components/schemas/ApiErrorDto" }
              }
            }
          },
          "500": {
            "description": "",
            "content": {
              "application/json": {
                "schema": { "$ref": "#/components/schemas/ApiErrorDto" }
              }
            }
          }
        },
        "summary": "",
        "tags": ["Legal gazette - public API"]
      }
    },
    "/api/v1/categories/slug/{slug}": {
      "get": {
        "operationId": "getCategoryBySlug",
        "parameters": [
          {
            "name": "slug",
            "required": true,
            "in": "path",
            "schema": { "type": "string" }
          }
        ],
        "responses": {
          "200": {
            "description": "",
            "content": {
              "application/json": {
                "schema": { "$ref": "#/components/schemas/CategoryDto" }
              }
            }
          },
          "400": {
            "description": "",
            "content": {
              "application/json": {
                "schema": { "$ref": "#/components/schemas/ApiErrorDto" }
              }
            }
          },
          "401": {
            "description": "",
            "content": {
              "application/json": {
                "schema": { "$ref": "#/components/schemas/ApiErrorDto" }
              }
            }
          },
          "403": {
            "description": "",
            "content": {
              "application/json": {
                "schema": { "$ref": "#/components/schemas/ApiErrorDto" }
              }
            }
          },
          "404": {
            "description": "",
            "content": {
              "application/json": {
                "schema": { "$ref": "#/components/schemas/ApiErrorDto" }
              }
            }
          },
          "500": {
            "description": "",
            "content": {
              "application/json": {
                "schema": { "$ref": "#/components/schemas/ApiErrorDto" }
              }
            }
          }
        },
        "summary": "",
        "tags": ["Legal gazette - public API"]
      }
    },
    "/api/v1/categories/{id}": {
      "get": {
        "operationId": "getCategory",
        "parameters": [
          {
            "name": "id",
            "required": true,
            "in": "path",
            "schema": { "type": "string" }
          }
        ],
        "responses": {
          "200": {
            "description": "",
            "content": {
              "application/json": {
                "schema": { "$ref": "#/components/schemas/CategoryDto" }
              }
            }
          },
          "400": {
            "description": "",
            "content": {
              "application/json": {
                "schema": { "$ref": "#/components/schemas/ApiErrorDto" }
              }
            }
          },
          "401": {
            "description": "",
            "content": {
              "application/json": {
                "schema": { "$ref": "#/components/schemas/ApiErrorDto" }
              }
            }
          },
          "403": {
            "description": "",
            "content": {
              "application/json": {
                "schema": { "$ref": "#/components/schemas/ApiErrorDto" }
              }
            }
          },
          "404": {
            "description": "",
            "content": {
              "application/json": {
                "schema": { "$ref": "#/components/schemas/ApiErrorDto" }
              }
            }
          },
          "500": {
            "description": "",
            "content": {
              "application/json": {
                "schema": { "$ref": "#/components/schemas/ApiErrorDto" }
              }
            }
          }
        },
        "summary": "",
        "tags": ["Legal gazette - public API"]
      }
    },
    "/api/v1/categories": {
      "get": {
        "operationId": "getCategories",
        "parameters": [
          {
            "name": "type",
            "required": false,
            "in": "query",
            "schema": { "nullable": true, "type": "string" }
          },
          {
            "name": "excludeUnassignable",
            "required": false,
            "in": "query",
            "description": "Filter out unassignable advert types",
            "schema": { "type": "boolean" }
          }
        ],
        "responses": {
          "200": {
            "description": "",
            "content": {
              "application/json": {
                "schema": { "$ref": "#/components/schemas/GetCategoriesDto" }
              }
            }
          },
          "400": {
            "description": "",
            "content": {
              "application/json": {
                "schema": { "$ref": "#/components/schemas/ApiErrorDto" }
              }
            }
          },
          "401": {
            "description": "",
            "content": {
              "application/json": {
                "schema": { "$ref": "#/components/schemas/ApiErrorDto" }
              }
            }
          },
          "403": {
            "description": "",
            "content": {
              "application/json": {
                "schema": { "$ref": "#/components/schemas/ApiErrorDto" }
              }
            }
          },
          "404": {
            "description": "",
            "content": {
              "application/json": {
                "schema": { "$ref": "#/components/schemas/ApiErrorDto" }
              }
            }
          },
          "500": {
            "description": "",
            "content": {
              "application/json": {
                "schema": { "$ref": "#/components/schemas/ApiErrorDto" }
              }
            }
          }
        },
        "summary": "",
        "tags": ["Legal gazette - public API"]
      }
    },
    "/api/v1/statuses": {
      "get": {
        "operationId": "getStatuses",
        "parameters": [],
        "responses": {
          "200": {
            "description": "",
            "content": {
              "application/json": {
                "schema": { "$ref": "#/components/schemas/GetStatusesDto" }
              }
            }
          },
          "400": {
            "description": "",
            "content": {
              "application/json": {
                "schema": { "$ref": "#/components/schemas/ApiErrorDto" }
              }
            }
          },
          "401": {
            "description": "",
            "content": {
              "application/json": {
                "schema": { "$ref": "#/components/schemas/ApiErrorDto" }
              }
            }
          },
          "403": {
            "description": "",
            "content": {
              "application/json": {
                "schema": { "$ref": "#/components/schemas/ApiErrorDto" }
              }
            }
          },
          "404": {
            "description": "",
            "content": {
              "application/json": {
                "schema": { "$ref": "#/components/schemas/ApiErrorDto" }
              }
            }
          },
          "500": {
            "description": "",
            "content": {
              "application/json": {
                "schema": { "$ref": "#/components/schemas/ApiErrorDto" }
              }
            }
          }
        },
        "summary": "",
        "tags": ["Legal gazette - public API"]
      }
    },
    "/api/v1/statuses/{id}": {
      "get": {
        "operationId": "getStatus",
        "parameters": [
          {
            "name": "id",
            "required": true,
            "in": "path",
            "schema": { "type": "string" }
          }
        ],
        "responses": {
          "200": {
            "description": "",
            "content": {
              "application/json": {
                "schema": { "$ref": "#/components/schemas/StatusDto" }
              }
            }
          },
          "400": {
            "description": "",
            "content": {
              "application/json": {
                "schema": { "$ref": "#/components/schemas/ApiErrorDto" }
              }
            }
          },
          "401": {
            "description": "",
            "content": {
              "application/json": {
                "schema": { "$ref": "#/components/schemas/ApiErrorDto" }
              }
            }
          },
          "403": {
            "description": "",
            "content": {
              "application/json": {
                "schema": { "$ref": "#/components/schemas/ApiErrorDto" }
              }
            }
          },
          "404": {
            "description": "",
            "content": {
              "application/json": {
                "schema": { "$ref": "#/components/schemas/ApiErrorDto" }
              }
            }
          },
          "500": {
            "description": "",
            "content": {
              "application/json": {
                "schema": { "$ref": "#/components/schemas/ApiErrorDto" }
              }
            }
          }
        },
        "summary": "",
        "tags": ["Legal gazette - public API"]
      }
    },
    "/api/v1/statuses/slug/{slug}": {
      "get": {
        "operationId": "getStatusBySlug",
        "parameters": [
          {
            "name": "slug",
            "required": true,
            "in": "path",
            "schema": { "type": "string" }
          }
        ],
        "responses": {
          "200": {
            "description": "",
            "content": {
              "application/json": {
                "schema": { "$ref": "#/components/schemas/StatusDto" }
              }
            }
          },
          "400": {
            "description": "",
            "content": {
              "application/json": {
                "schema": { "$ref": "#/components/schemas/ApiErrorDto" }
              }
            }
          },
          "401": {
            "description": "",
            "content": {
              "application/json": {
                "schema": { "$ref": "#/components/schemas/ApiErrorDto" }
              }
            }
          },
          "403": {
            "description": "",
            "content": {
              "application/json": {
                "schema": { "$ref": "#/components/schemas/ApiErrorDto" }
              }
            }
          },
          "404": {
            "description": "",
            "content": {
              "application/json": {
                "schema": { "$ref": "#/components/schemas/ApiErrorDto" }
              }
            }
          },
          "500": {
            "description": "",
            "content": {
              "application/json": {
                "schema": { "$ref": "#/components/schemas/ApiErrorDto" }
              }
            }
          }
        },
        "summary": "",
        "tags": ["Legal gazette - public API"]
      }
    },
    "/api/v1/court-districts": {
      "get": {
        "operationId": "getCourtDistricts",
        "parameters": [],
        "responses": {
          "200": {
            "description": "",
            "content": {
              "application/json": {
                "schema": {
                  "$ref": "#/components/schemas/GetCourtDistrictsDto"
                }
              }
            }
          },
          "400": {
            "description": "",
            "content": {
              "application/json": {
                "schema": { "$ref": "#/components/schemas/ApiErrorDto" }
              }
            }
          },
          "401": {
            "description": "",
            "content": {
              "application/json": {
                "schema": { "$ref": "#/components/schemas/ApiErrorDto" }
              }
            }
          },
          "403": {
            "description": "",
            "content": {
              "application/json": {
                "schema": { "$ref": "#/components/schemas/ApiErrorDto" }
              }
            }
          },
          "404": {
            "description": "",
            "content": {
              "application/json": {
                "schema": { "$ref": "#/components/schemas/ApiErrorDto" }
              }
            }
          },
          "500": {
            "description": "",
            "content": {
              "application/json": {
                "schema": { "$ref": "#/components/schemas/ApiErrorDto" }
              }
            }
          }
        },
        "summary": "",
        "tags": ["Legal gazette - public API"]
      }
    },
    "/api/v1/court-districts/{id}": {
      "get": {
        "operationId": "getCourtDistrictById",
        "parameters": [
          {
            "name": "id",
            "required": true,
            "in": "path",
            "schema": { "type": "string" }
          }
        ],
        "responses": {
          "200": {
            "description": "",
            "content": {
              "application/json": {
                "schema": { "$ref": "#/components/schemas/CourtDistrictDto" }
              }
            }
          },
          "400": {
            "description": "",
            "content": {
              "application/json": {
                "schema": { "$ref": "#/components/schemas/ApiErrorDto" }
              }
            }
          },
          "401": {
            "description": "",
            "content": {
              "application/json": {
                "schema": { "$ref": "#/components/schemas/ApiErrorDto" }
              }
            }
          },
          "403": {
            "description": "",
            "content": {
              "application/json": {
                "schema": { "$ref": "#/components/schemas/ApiErrorDto" }
              }
            }
          },
          "404": {
            "description": "",
            "content": {
              "application/json": {
                "schema": { "$ref": "#/components/schemas/ApiErrorDto" }
              }
            }
          },
          "500": {
            "description": "",
            "content": {
              "application/json": {
                "schema": { "$ref": "#/components/schemas/ApiErrorDto" }
              }
            }
          }
        },
        "summary": "",
        "tags": ["Legal gazette - public API"]
      }
    },
    "/api/v1/court-districts/slug/{slug}": {
      "get": {
        "operationId": "getCourtDistrictBySlug",
        "parameters": [
          {
            "name": "slug",
            "required": true,
            "in": "path",
            "schema": { "type": "string" }
          }
        ],
        "responses": {
          "200": {
            "description": "",
            "content": {
              "application/json": {
                "schema": { "$ref": "#/components/schemas/CourtDistrictDto" }
              }
            }
          },
          "400": {
            "description": "",
            "content": {
              "application/json": {
                "schema": { "$ref": "#/components/schemas/ApiErrorDto" }
              }
            }
          },
          "401": {
            "description": "",
            "content": {
              "application/json": {
                "schema": { "$ref": "#/components/schemas/ApiErrorDto" }
              }
            }
          },
          "403": {
            "description": "",
            "content": {
              "application/json": {
                "schema": { "$ref": "#/components/schemas/ApiErrorDto" }
              }
            }
          },
          "404": {
            "description": "",
            "content": {
              "application/json": {
                "schema": { "$ref": "#/components/schemas/ApiErrorDto" }
              }
            }
          },
          "500": {
            "description": "",
            "content": {
              "application/json": {
                "schema": { "$ref": "#/components/schemas/ApiErrorDto" }
              }
            }
          }
        },
        "summary": "",
        "tags": ["Legal gazette - public API"]
      }
    },
    "/api/v1/publications": {
      "get": {
        "operationId": "getPublications",
        "parameters": [
          {
            "name": "page",
            "required": false,
            "in": "query",
            "schema": { "default": 1, "example": 1, "type": "number" }
          },
          {
            "name": "pageSize",
            "required": false,
            "in": "query",
            "schema": { "default": 10, "example": 10, "type": "number" }
          },
          {
            "name": "advertId",
            "required": false,
            "in": "query",
            "schema": { "type": "string" }
          },
          {
            "name": "search",
            "required": false,
            "in": "query",
            "schema": { "type": "string" }
          },
          {
            "name": "categoryId",
            "required": false,
            "in": "query",
            "schema": { "type": "array", "items": { "type": "string" } }
          },
          {
            "name": "typeId",
            "required": false,
            "in": "query",
            "schema": { "type": "string" }
          },
          {
            "name": "dateFrom",
            "required": false,
            "in": "query",
            "schema": { "type": "string" }
          },
          {
            "name": "dateTo",
            "required": false,
            "in": "query",
            "schema": { "type": "string" }
          },
          {
            "name": "pdfUrl",
            "required": false,
            "in": "query",
            "schema": { "type": "string" }
          }
        ],
        "responses": {
          "200": {
            "description": "",
            "content": {
              "application/json": {
                "schema": { "$ref": "#/components/schemas/GetPublicationsDto" }
              }
            }
          },
          "400": {
            "description": "",
            "content": {
              "application/json": {
                "schema": { "$ref": "#/components/schemas/ApiErrorDto" }
              }
            }
          },
          "401": {
            "description": "",
            "content": {
              "application/json": {
                "schema": { "$ref": "#/components/schemas/ApiErrorDto" }
              }
            }
          },
          "403": {
            "description": "",
            "content": {
              "application/json": {
                "schema": { "$ref": "#/components/schemas/ApiErrorDto" }
              }
            }
          },
          "404": {
            "description": "",
            "content": {
              "application/json": {
                "schema": { "$ref": "#/components/schemas/ApiErrorDto" }
              }
            }
          },
          "500": {
            "description": "",
            "content": {
              "application/json": {
                "schema": { "$ref": "#/components/schemas/ApiErrorDto" }
              }
            }
          }
        },
        "summary": "",
        "tags": ["Legal gazette - public API"]
      }
    },
    "/api/v1/publications/adverts/{advertId}/{version}": {
      "get": {
        "operationId": "getAdvertPublication",
        "parameters": [
          {
            "name": "advertId",
            "required": true,
            "in": "path",
            "schema": { "type": "string" }
          },
          {
            "name": "version",
            "required": true,
            "in": "path",
            "schema": { "enum": ["A", "B", "C"], "type": "string" }
          }
        ],
        "responses": {
          "200": {
            "description": "",
            "content": {
              "application/json": {
                "schema": {
                  "$ref": "#/components/schemas/AdvertPublicationDetailedDto"
                }
              }
            }
          },
          "400": {
            "description": "",
            "content": {
              "application/json": {
                "schema": { "$ref": "#/components/schemas/ApiErrorDto" }
              }
            }
          },
          "401": {
            "description": "",
            "content": {
              "application/json": {
                "schema": { "$ref": "#/components/schemas/ApiErrorDto" }
              }
            }
          },
          "403": {
            "description": "",
            "content": {
              "application/json": {
                "schema": { "$ref": "#/components/schemas/ApiErrorDto" }
              }
            }
          },
          "404": {
            "description": "",
            "content": {
              "application/json": {
                "schema": { "$ref": "#/components/schemas/ApiErrorDto" }
              }
            }
          },
          "500": {
            "description": "",
            "content": {
              "application/json": {
                "schema": { "$ref": "#/components/schemas/ApiErrorDto" }
              }
            }
          }
        },
        "summary": "",
        "tags": ["Legal gazette - public API"]
      }
    },
    "/api/v1/publications/adverts/{advertId}": {
      "post": {
        "operationId": "createAdvertPublication",
        "parameters": [
          {
            "name": "advertId",
            "required": true,
            "in": "path",
            "schema": { "type": "string" }
          }
        ],
        "responses": {
          "204": { "description": "" },
          "400": {
            "description": "",
            "content": {
              "application/json": {
                "schema": { "$ref": "#/components/schemas/ApiErrorDto" }
              }
            }
          },
          "401": {
            "description": "",
            "content": {
              "application/json": {
                "schema": { "$ref": "#/components/schemas/ApiErrorDto" }
              }
            }
          },
          "403": {
            "description": "",
            "content": {
              "application/json": {
                "schema": { "$ref": "#/components/schemas/ApiErrorDto" }
              }
            }
          },
          "404": {
            "description": "",
            "content": {
              "application/json": {
                "schema": { "$ref": "#/components/schemas/ApiErrorDto" }
              }
            }
          },
          "500": {
            "description": "",
            "content": {
              "application/json": {
                "schema": { "$ref": "#/components/schemas/ApiErrorDto" }
              }
            }
          }
        },
        "summary": "",
        "tags": ["Legal gazette - public API"]
      }
    },
    "/api/v1/publications/{publicationId}/adverts/{advertId}/publish": {
      "post": {
        "operationId": "publishAdvertPublication",
        "parameters": [
          {
            "name": "advertId",
            "required": true,
            "in": "path",
            "schema": { "type": "string" }
          },
          {
            "name": "publicationId",
            "required": true,
            "in": "path",
            "schema": { "type": "string" }
          }
        ],
        "responses": {
          "204": { "description": "" },
          "400": {
            "description": "",
            "content": {
              "application/json": {
                "schema": { "$ref": "#/components/schemas/ApiErrorDto" }
              }
            }
          },
          "401": {
            "description": "",
            "content": {
              "application/json": {
                "schema": { "$ref": "#/components/schemas/ApiErrorDto" }
              }
            }
          },
          "403": {
            "description": "",
            "content": {
              "application/json": {
                "schema": { "$ref": "#/components/schemas/ApiErrorDto" }
              }
            }
          },
          "404": {
            "description": "",
            "content": {
              "application/json": {
                "schema": { "$ref": "#/components/schemas/ApiErrorDto" }
              }
            }
          },
          "500": {
            "description": "",
            "content": {
              "application/json": {
                "schema": { "$ref": "#/components/schemas/ApiErrorDto" }
              }
            }
          }
        },
        "summary": "",
        "tags": ["Legal gazette - public API"]
      }
    },
    "/api/v1/publications/{publicationId}/adverts/{advertId}": {
      "patch": {
        "operationId": "updateAdvertPublication",
        "parameters": [
          {
            "name": "advertId",
            "required": true,
            "in": "path",
            "schema": { "type": "string" }
          },
          {
            "name": "publicationId",
            "required": true,
            "in": "path",
            "schema": { "type": "string" }
          }
        ],
        "requestBody": {
          "required": true,
          "content": {
            "application/json": {
              "schema": {
                "$ref": "#/components/schemas/UpdateAdvertPublicationDto"
              }
            }
          }
        },
        "responses": {
          "204": { "description": "" },
          "400": {
            "description": "",
            "content": {
              "application/json": {
                "schema": { "$ref": "#/components/schemas/ApiErrorDto" }
              }
            }
          },
          "401": {
            "description": "",
            "content": {
              "application/json": {
                "schema": { "$ref": "#/components/schemas/ApiErrorDto" }
              }
            }
          },
          "403": {
            "description": "",
            "content": {
              "application/json": {
                "schema": { "$ref": "#/components/schemas/ApiErrorDto" }
              }
            }
          },
          "404": {
            "description": "",
            "content": {
              "application/json": {
                "schema": { "$ref": "#/components/schemas/ApiErrorDto" }
              }
            }
          },
          "500": {
            "description": "",
            "content": {
              "application/json": {
                "schema": { "$ref": "#/components/schemas/ApiErrorDto" }
              }
            }
          }
        },
        "summary": "",
        "tags": ["Legal gazette - public API"]
      },
      "delete": {
        "operationId": "deleteAdvertPublication",
        "parameters": [
          {
            "name": "advertId",
            "required": true,
            "in": "path",
            "schema": { "type": "string" }
          },
          {
            "name": "publicationId",
            "required": true,
            "in": "path",
            "schema": { "type": "string" }
          }
        ],
        "responses": {
          "204": { "description": "" },
          "400": {
            "description": "",
            "content": {
              "application/json": {
                "schema": { "$ref": "#/components/schemas/ApiErrorDto" }
              }
            }
          },
          "401": {
            "description": "",
            "content": {
              "application/json": {
                "schema": { "$ref": "#/components/schemas/ApiErrorDto" }
              }
            }
          },
          "403": {
            "description": "",
            "content": {
              "application/json": {
                "schema": { "$ref": "#/components/schemas/ApiErrorDto" }
              }
            }
          },
          "404": {
            "description": "",
            "content": {
              "application/json": {
                "schema": { "$ref": "#/components/schemas/ApiErrorDto" }
              }
            }
          },
          "500": {
            "description": "",
            "content": {
              "application/json": {
                "schema": { "$ref": "#/components/schemas/ApiErrorDto" }
              }
            }
          }
        },
        "summary": "",
        "tags": ["Legal gazette - public API"]
      }
    },
    "/api/v1/subscribers/me": {
      "get": {
        "operationId": "getMySubscriber",
        "parameters": [],
        "responses": {
          "200": {
            "description": "",
            "content": {
              "application/json": {
                "schema": { "$ref": "#/components/schemas/SubscriberDto" }
              }
            }
          },
          "400": {
            "description": "",
            "content": {
              "application/json": {
                "schema": { "$ref": "#/components/schemas/ApiErrorDto" }
              }
            }
          },
          "401": {
            "description": "",
            "content": {
              "application/json": {
                "schema": { "$ref": "#/components/schemas/ApiErrorDto" }
              }
            }
          },
          "403": {
            "description": "",
            "content": {
              "application/json": {
                "schema": { "$ref": "#/components/schemas/ApiErrorDto" }
              }
            }
          },
          "404": {
            "description": "",
            "content": {
              "application/json": {
                "schema": { "$ref": "#/components/schemas/ApiErrorDto" }
              }
            }
          },
          "500": {
            "description": "",
            "content": {
              "application/json": {
                "schema": { "$ref": "#/components/schemas/ApiErrorDto" }
              }
            }
          }
        },
        "security": [{ "bearer": [] }],
        "summary": "",
        "tags": ["Legal gazette - public API"]
      }
    }
  },
  "info": {
    "title": "The Legal Gazette of Iceland API",
    "description": "The Legal Gazette of Iceland API",
    "version": "1.0",
    "contact": {}
  },
  "tags": [{ "name": "Legal gazette - public API" }],
  "servers": [],
  "components": {
    "securitySchemes": {
      "bearer": { "scheme": "bearer", "bearerFormat": "JWT", "type": "http" }
    },
    "schemas": {
      "TypeModel": { "type": "object", "properties": {} },
      "ApiErrorDto": {
        "type": "object",
        "properties": {
          "statusCode": { "type": "number" },
          "timestamp": { "type": "string" },
          "name": {
            "type": "string",
            "enum": [
              "NotFound",
              "ValidationError",
              "ForeignKeyConstraintError",
              "UniqueConstraintError",
              "TimeoutError",
              "Unauthorized",
              "Forbidden",
              "BadRequest",
              "InternalServerError",
              "UnknownError"
            ],
            "example": [
              "NotFound",
              "ValidationError",
              "ForeignKeyConstraintError",
              "UniqueConstraintError",
              "TimeoutError",
              "Unauthorized",
              "Forbidden",
              "BadRequest",
              "InternalServerError",
              "UnknownError"
            ]
          },
          "message": { "type": "string" },
          "details": { "type": "array", "items": { "type": "string" } }
        },
        "required": ["statusCode", "timestamp"]
      },
      "TypeDto": {
        "type": "object",
        "properties": {
          "id": {
            "type": "string",
            "description": "UUIDV4 of the entity",
            "example": "182391f7-d355-46f0-bcee-4d8baa68b55d"
          },
          "title": {
            "type": "string",
            "description": "Title of the entity",
            "example": "Base entity"
          },
          "slug": {
            "type": "string",
            "description": "Slug of the entity",
            "example": "base-entity"
          }
        },
        "required": ["id", "title", "slug"]
      },
      "GetTypesDto": {
        "type": "object",
        "properties": {
          "types": {
            "type": "array",
            "items": { "$ref": "#/components/schemas/TypeDto" }
          }
        },
        "required": ["types"]
      },
      "CategoryDto": {
        "type": "object",
        "properties": {
          "id": {
            "type": "string",
            "description": "UUIDV4 of the entity",
            "example": "182391f7-d355-46f0-bcee-4d8baa68b55d"
          },
          "title": {
            "type": "string",
            "description": "Title of the entity",
            "example": "Base entity"
          },
          "slug": {
            "type": "string",
            "description": "Slug of the entity",
            "example": "base-entity"
          }
        },
        "required": ["id", "title", "slug"]
      },
      "GetCategoriesDto": {
        "type": "object",
        "properties": {
          "categories": {
            "type": "array",
            "items": { "$ref": "#/components/schemas/CategoryDto" }
          }
        },
        "required": ["categories"]
      },
      "BaseEntityDto": {
        "type": "object",
        "properties": {
          "id": {
            "type": "string",
            "description": "UUIDV4 of the entity",
            "example": "182391f7-d355-46f0-bcee-4d8baa68b55d"
          },
          "title": {
            "type": "string",
            "description": "Title of the entity",
            "example": "Base entity"
          },
          "slug": {
            "type": "string",
            "description": "Slug of the entity",
            "example": "base-entity"
          }
        },
        "required": ["id", "title", "slug"]
      },
      "GetStatusesDto": {
        "type": "object",
        "properties": {
          "statuses": {
            "type": "array",
            "items": { "$ref": "#/components/schemas/BaseEntityDto" }
          }
        },
        "required": ["statuses"]
      },
      "StatusIdEnum": {
        "type": "string",
        "enum": [
          "63726fce-edcf-412d-85e8-087e99c592f2",
          "cd3bf301-52a1-493e-8c80-a391c310c840",
          "a2f3b1c4-2d5e-4a7b-8c6f-9d1e0f3a2b8c",
          "bd835a1d-0ecb-4aa4-9910-b5e60c30dced",
          "f3a0b1c4-2d5e-4a7b-8c6f-9d1e0f3a2b8c",
          "e2f3b1c4-2d5e-4a7b-8c6f-9d1e0f3a2b8c"
        ]
      },
      "StatusEnum": {
        "type": "string",
        "enum": [
          "Drög",
          "Innsent",
          "Tilbúið til útgáfu",
          "Útgefið",
          "Hafnað",
          "Afturkallað"
        ]
      },
      "StatusDto": {
        "type": "object",
        "properties": {
          "id": { "allOf": [{ "$ref": "#/components/schemas/StatusIdEnum" }] },
          "title": { "allOf": [{ "$ref": "#/components/schemas/StatusEnum" }] },
          "slug": { "type": "string" }
        },
        "required": ["id", "title", "slug"]
      },
      "CourtDistrictDto": {
        "type": "object",
        "properties": {
          "id": {
            "type": "string",
            "description": "UUIDV4 of the entity",
            "example": "182391f7-d355-46f0-bcee-4d8baa68b55d"
          },
          "title": {
            "type": "string",
            "description": "Title of the entity",
            "example": "Base entity"
          },
          "slug": {
            "type": "string",
            "description": "Slug of the entity",
            "example": "base-entity"
          }
        },
        "required": ["id", "title", "slug"]
      },
      "GetCourtDistrictsDto": {
        "type": "object",
        "properties": {
          "courtDistricts": {
            "type": "array",
            "items": { "$ref": "#/components/schemas/CourtDistrictDto" }
          }
        },
        "required": ["courtDistricts"]
      },
      "AdvertVersionEnum": { "type": "string", "enum": ["A", "B", "C"] },
      "PublishedPublicationDto": {
        "type": "object",
        "properties": {
          "id": { "type": "string" },
          "advertId": { "type": "string" },
          "publishedAt": { "type": "string" },
          "title": { "type": "string" },
          "type": { "$ref": "#/components/schemas/TypeDto" },
          "category": { "$ref": "#/components/schemas/CategoryDto" },
          "version": {
            "allOf": [{ "$ref": "#/components/schemas/AdvertVersionEnum" }]
          },
          "publicationNumber": { "type": "string" },
          "createdBy": { "type": "string" },
          "isLegacy": { "type": "boolean" },
          "pdfUrl": { "type": "string", "nullable": true }
        },
        "required": [
          "id",
          "advertId",
          "publishedAt",
          "title",
          "type",
          "category",
          "version",
          "publicationNumber",
          "createdBy",
          "isLegacy",
          "pdfUrl"
        ]
      },
      "Paging": {
        "type": "object",
        "properties": {
          "page": { "type": "number", "example": 1 },
          "totalPages": { "type": "number", "example": 10 },
          "totalItems": { "type": "number", "example": 1000 },
          "nextPage": { "type": "number", "example": 2, "nullable": true },
          "previousPage": { "type": "number", "example": 1, "nullable": true },
          "pageSize": {
            "type": "number",
            "example": 10,
            "minimum": 1,
            "maximum": 100
          },
          "hasNextPage": { "type": "boolean", "example": true },
          "hasPreviousPage": { "type": "boolean", "example": false }
        },
        "required": [
          "page",
          "totalPages",
          "totalItems",
          "nextPage",
          "previousPage",
          "pageSize",
          "hasNextPage",
          "hasPreviousPage"
        ]
      },
      "GetPublicationsDto": {
        "type": "object",
        "properties": {
          "publications": {
            "type": "array",
            "items": { "$ref": "#/components/schemas/PublishedPublicationDto" }
          },
          "paging": { "$ref": "#/components/schemas/Paging" }
        },
        "required": ["publications", "paging"]
      },
      "AdvertPublicationDto": {
        "type": "object",
        "properties": {
          "id": { "type": "string" },
          "advertId": { "type": "string" },
          "scheduledAt": { "type": "string" },
          "publishedAt": { "type": "string", "nullable": true },
          "version": {
            "allOf": [{ "$ref": "#/components/schemas/AdvertVersionEnum" }]
          },
          "isLegacy": { "type": "boolean" },
          "pdfUrl": { "type": "string", "nullable": true }
        },
        "required": [
          "id",
          "advertId",
          "scheduledAt",
          "publishedAt",
          "version",
          "isLegacy",
          "pdfUrl"
        ]
      },
      "AdvertDto": {
        "type": "object",
        "properties": {
          "createdAt": {
            "type": "string",
            "description": "ISO representation of the creation date",
            "example": "2021-08-31T12:00:00.000Z"
          },
          "updatedAt": {
            "type": "string",
            "description": "ISO representation of the updated date",
            "example": "2021-08-31T12:00:00.000Z"
          },
          "deletedAt": {
            "type": "string",
            "description": "ISO representation of the deletion date",
            "example": "2021-08-31T12:00:00.000Z",
            "nullable": true
          },
          "id": { "type": "string" },
          "scheduledAt": { "type": "string" },
          "category": { "$ref": "#/components/schemas/CategoryDto" },
          "type": { "$ref": "#/components/schemas/TypeDto" },
          "status": { "$ref": "#/components/schemas/StatusDto" },
          "title": { "type": "string" },
          "createdBy": { "type": "string" },
          "assignedUser": { "type": "string" },
          "publications": {
            "type": "array",
            "items": { "$ref": "#/components/schemas/AdvertPublicationDto" }
          }
        },
        "required": [
          "createdAt",
          "updatedAt",
          "id",
          "scheduledAt",
          "category",
          "type",
          "status",
          "title",
          "createdBy",
          "publications"
        ]
      },
      "AdvertPublicationDetailedDto": {
        "type": "object",
        "properties": {
          "publication": {
            "$ref": "#/components/schemas/AdvertPublicationDto"
          },
          "advert": { "$ref": "#/components/schemas/AdvertDto" },
          "html": { "type": "string" }
        },
        "required": ["publication", "advert", "html"]
      },
      "UpdateAdvertPublicationDto": {
        "type": "object",
        "properties": { "scheduledAt": { "type": "string" } },
        "required": ["scheduledAt"]
      },
      "SubscriberDto": {
        "type": "object",
        "properties": {
          "id": { "type": "string" },
          "nationalId": { "type": "string" },
          "isActive": { "type": "boolean" }
        },
        "required": ["id", "nationalId", "isActive"]
      }
    }
  }
}
